CWDoublePendulum/__init__.py
CWDoublePendulum/manualRun.py
CWDoublePendulum/sim.py
CWDoublePendulum/testHash.txt
cw_doublependulum-0.3.2.dist-info/licenses/LICENSE
cw_doublependulum-0.3.2.dist-info/METADATA
cw_doublependulum-0.3.2.dist-info/WHEEL
cw_doublependulum-0.3.2.dist-info/entry_points.txt
cw_doublependulum-0.3.2.dist-info/top_level.txt
cw_doublependulum-0.3.2.dist-info/RECORD
