Metadata-Version: 2.4
Name: CW-DoublePendulum
Version: 0.3.2
Summary: A Python package that uses NumPy and Matplotlib to simulate an interactive double pendulum.
Author-email: Chase Worsley <worsleychase@gmail.com>
License: MIT
Project-URL: Homepage, https://github.com/Worsleychase/InteractiveDoublePendulum
Classifier: Programming Language :: Python :: 3
Classifier: License :: OSI Approved :: MIT License
Classifier: Operating System :: OS Independent
Requires-Python: >=3.9
License-File: LICENSE
Requires-Dist: numpy
Requires-Dist: matplotlib
Dynamic: license-file
